django_registration_with_email
