Metadata-Version: 1.1
Name: django-registration-with-email
Version: 0.3.1
Summary: Override Django-registration to log in by e-mail
Home-page: https://github.com/PetrDlouhy/django-registration-with-email
Author: Petr Dlouhý
Author-email: petr.dlouhy@email.cz
License: MIT
Keywords: django-registration-with-email
Platform: UNKNOWN
Classifier: Development Status :: 3 - Alpha
Classifier: Framework :: Django :: 1.11
Classifier: Framework :: Django :: 2.1
Classifier: Intended Audience :: Developers
Classifier: License :: OSI Approved :: BSD License
Classifier: Natural Language :: English
Classifier: Programming Language :: Python :: 2
Classifier: Programming Language :: Python :: 2.7
Classifier: Programming Language :: Python :: 3
Classifier: Programming Language :: Python :: 3.5
Classifier: Programming Language :: Python :: 3.6
